{"_invocation_id": "8f6e4bba-426e-447b-a94f-b1a41709ea30", "linked": {"0": {"name": "model.dataton_s1.stg_s1_interes_participacion", "type": "model"}, "1": {"name": "model.dataton_s1.stg_s1_inmuebles", "type": "model"}, "2": {"name": "model.dataton_s1.stg_s1_interes_apoyos", "type": "model"}, "3": {"name": "model.dataton_s1.stg_s1_vehiculos", "type": "model"}, "4": {"name": "model.dataton_s1.s1_ingresos_limpios", "type": "model", "succ": [11]}, "5": {"name": "model.dataton_s1.int_s1_ingresos_clasificados", "type": "model", "succ": [4, 6]}, "6": {"name": "model.dataton_s1.audit_s1_ingresos_rechazados", "type": "model"}, "7": {"name": "model.dataton_s1.stg_s1_ingresos", "type": "model", "succ": [5]}, "8": {"name": "model.dataton_s1.s1_declaraciones_perfil", "type": "model", "succ": [11]}, "9": {"name": "model.dataton_s1.int_s1_declaraciones_normalizadas", "type": "model", "succ": [8]}, "10": {"name": "model.dataton_s1.stg_s1_declaraciones", "type": "model", "succ": [9]}, "11": {"name": "model.dataton_s1.s1_dataset_maestro", "type": "model"}, "12": {"name": "model.dataton_s1.stg_s1_prestamo_comodato", "type": "model"}, "13": {"name": "model.dataton_s1.stg_s1_dependientes_economicos", "type": "model"}, "14": {"name": "model.dataton_s1.stg_s1_datos_pareja", "type": "model"}, "15": {"name": "model.dataton_s1.stg_s1_inversiones", "type": "model"}, "16": {"name": "model.dataton_s1.stg_s1_experiencia_laboral", "type": "model"}, "17": {"name": "model.dataton_s1.stg_s1_adeudos_pasivos", "type": "model"}, "18": {"name": "model.dataton_s1.stg_s1_bienes_muebles", "type": "model"}}}